[
  {
    "id": "5093348712120320",
    "browser_name": "safari",
    "browser_version": "26.5 (21624.2.5.11.4)",
    "os_name": "mac",
    "os_version": "26.5",
    "revision": "c05b447326",
    "full_revision_hash": "c05b447326585237713013c66341eab2cdf967b6",
    "created_at": "2026-05-18T10:07:25.744944+00:00",
    "time_start": "2026-05-18T06:56:52.790000+00:00",
    "results_url": "https://storage.googleapis.com/wptd/c05b447326585237713013c66341eab2cdf967b6/safari-26.5__21624.2.5.11.4_-mac-26.5-6dd7fabe61-summary_v2.json.gz",
    "time_end": "2026-05-18T09:44:13.392000+00:00",
    "raw_results_url": "https://storage.googleapis.com/wptd-results/c05b447326585237713013c66341eab2cdf967b6/safari-26.5__21624.2.5.11.4_-mac-26.5-6dd7fabe61/report.json",
    "labels": [
      "github-actions",
      "master",
      "safari",
      "stable"
    ]
  }
]