[
  {
    "id": "5167274966384640",
    "browser_name": "chrome",
    "browser_version": "146.0.7654.0",
    "os_name": "linux",
    "os_version": "22.04",
    "revision": "2e2e15b1d4",
    "full_revision_hash": "2e2e15b1d44551c5798cdd2f26d846f426eb6856",
    "created_at": "2026-01-28T06:27:09.859179+00:00",
    "time_start": "2026-01-28T02:19:45.880000+00:00",
    "results_url": "https://storage.googleapis.com/wptd/2e2e15b1d44551c5798cdd2f26d846f426eb6856/chrome-146.0.7654.0-linux-22.04-83516ecf7d-summary_v2.json.gz",
    "time_end": "2026-01-28T05:59:45.275000+00:00",
    "raw_results_url": "https://storage.googleapis.com/wptd-results/2e2e15b1d44551c5798cdd2f26d846f426eb6856/chrome-146.0.7654.0-linux-22.04-83516ecf7d/report.json",
    "labels": [
      "canary",
      "chrome",
      "experimental",
      "master",
      "taskcluster",
      "user:chromium-wpt-export-bot"
    ]
  },
  {
    "id": "5100823232380928",
    "browser_name": "firefox",
    "browser_version": "149.0a1",
    "os_name": "linux",
    "os_version": "22.04",
    "revision": "2e2e15b1d4",
    "full_revision_hash": "2e2e15b1d44551c5798cdd2f26d846f426eb6856",
    "created_at": "2026-01-28T03:50:10.014082+00:00",
    "time_start": "2026-01-28T02:22:10.957000+00:00",
    "results_url": "https://storage.googleapis.com/wptd/2e2e15b1d44551c5798cdd2f26d846f426eb6856/firefox-149.0a1-linux-22.04-7cc3226cd7-summary_v2.json.gz",
    "time_end": "2026-01-28T03:24:02.985000+00:00",
    "raw_results_url": "https://storage.googleapis.com/wptd-results/2e2e15b1d44551c5798cdd2f26d846f426eb6856/firefox-149.0a1-linux-22.04-7cc3226cd7/report.json",
    "labels": [
      "experimental",
      "firefox",
      "master",
      "nightly",
      "taskcluster",
      "user:chromium-wpt-export-bot"
    ]
  }
]