[
  {
    "id": 5137911595139072,
    "browser_name": "chrome",
    "browser_version": "128.0.6571.0",
    "os_name": "linux",
    "os_version": "20.04",
    "revision": "57308167a6",
    "full_revision_hash": "57308167a6128fbf7e2c80d2f5e67321f8c48eff",
    "results_url": "https://storage.googleapis.com/wptd/57308167a6128fbf7e2c80d2f5e67321f8c48eff/chrome-128.0.6571.0-linux-20.04-b336886b34-summary_v2.json.gz",
    "created_at": "2024-07-02T19:48:03.451728+00:00",
    "time_start": "2024-07-02T16:08:01.756000+00:00",
    "time_end": "2024-07-02T17:30:20.597000+00:00",
    "raw_results_url": "https://storage.googleapis.com/wptd-results/57308167a6128fbf7e2c80d2f5e67321f8c48eff/chrome-128.0.6571.0-linux-20.04-b336886b34/report.json",
    "labels": [
      "canary",
      "chrome",
      "experimental",
      "master",
      "taskcluster",
      "user:chromium-wpt-export-bot"
    ]
  },
  {
    "id": 5169911685185536,
    "browser_name": "firefox",
    "browser_version": "129.0a1",
    "os_name": "linux",
    "os_version": "20.04",
    "revision": "57308167a6",
    "full_revision_hash": "57308167a6128fbf7e2c80d2f5e67321f8c48eff",
    "results_url": "https://storage.googleapis.com/wptd/57308167a6128fbf7e2c80d2f5e67321f8c48eff/firefox-129.0a1-linux-20.04-b0446fe271-summary_v2.json.gz",
    "created_at": "2024-07-02T19:34:36.258642+00:00",
    "time_start": "2024-07-02T16:28:18.441000+00:00",
    "time_end": "2024-07-02T17:30:37.442000+00:00",
    "raw_results_url": "https://storage.googleapis.com/wptd-results/57308167a6128fbf7e2c80d2f5e67321f8c48eff/firefox-129.0a1-linux-20.04-b0446fe271/report.json",
    "labels": [
      "experimental",
      "firefox",
      "master",
      "nightly",
      "taskcluster",
      "user:chromium-wpt-export-bot"
    ]
  }
]