[
  {
    "id": 4807021271973888,
    "browser_name": "chrome",
    "browser_version": "120.0.6090.0 dev",
    "os_name": "linux",
    "os_version": "20.04",
    "revision": "e78bb4c11a",
    "full_revision_hash": "e78bb4c11a870c0353cebab8ad85142931419fb1",
    "results_url": "https://storage.googleapis.com/wptd/e78bb4c11a870c0353cebab8ad85142931419fb1/chrome-120.0.6090.0_dev-linux-20.04-a6bd1446d2-summary_v2.json.gz",
    "created_at": "2023-10-31T20:38:58.213022+00:00",
    "time_start": "2023-10-31T19:02:55.753000+00:00",
    "time_end": "2023-10-31T20:25:03.582000+00:00",
    "raw_results_url": "https://storage.googleapis.com/wptd-results/e78bb4c11a870c0353cebab8ad85142931419fb1/chrome-120.0.6090.0_dev-linux-20.04-a6bd1446d2/report.json",
    "labels": [
      "chrome",
      "dev",
      "experimental",
      "master",
      "taskcluster",
      "user:spectranaut"
    ]
  },
  {
    "id": 5075958333177856,
    "browser_name": "firefox",
    "browser_version": "121.0a1",
    "os_name": "linux",
    "os_version": "20.04",
    "revision": "e78bb4c11a",
    "full_revision_hash": "e78bb4c11a870c0353cebab8ad85142931419fb1",
    "results_url": "https://storage.googleapis.com/wptd/e78bb4c11a870c0353cebab8ad85142931419fb1/firefox-121.0a1-linux-20.04-cc74c4c48a-summary_v2.json.gz",
    "created_at": "2023-10-31T20:48:05.209218+00:00",
    "time_start": "2023-10-31T19:06:05.396000+00:00",
    "time_end": "2023-10-31T20:11:12.427000+00:00",
    "raw_results_url": "https://storage.googleapis.com/wptd-results/e78bb4c11a870c0353cebab8ad85142931419fb1/firefox-121.0a1-linux-20.04-cc74c4c48a/report.json",
    "labels": [
      "experimental",
      "firefox",
      "master",
      "nightly",
      "taskcluster",
      "user:spectranaut"
    ]
  }
]