[
  {
    "id": 5086991641477120,
    "browser_name": "firefox",
    "browser_version": "133.0a1",
    "os_name": "linux",
    "os_version": "20.04",
    "revision": "c8bf0721b9",
    "full_revision_hash": "c8bf0721b97644be612635c67c66275f8aa2c0c4",
    "results_url": "https://storage.googleapis.com/wptd/c8bf0721b97644be612635c67c66275f8aa2c0c4/firefox-133.0a1-linux-20.04-944ebfb6d8-summary_v2.json.gz",
    "created_at": "2024-10-09T22:52:44.166016+00:00",
    "time_start": "2024-10-09T20:59:40.136000+00:00",
    "time_end": "2024-10-09T22:04:39.719000+00:00",
    "raw_results_url": "https://storage.googleapis.com/wptd-results/c8bf0721b97644be612635c67c66275f8aa2c0c4/firefox-133.0a1-linux-20.04-944ebfb6d8/report.json",
    "labels": [
      "experimental",
      "firefox",
      "master",
      "nightly",
      "taskcluster",
      "user:chromium-wpt-export-bot"
    ]
  }
]