[
  {
    "id": "5078577450319872",
    "browser_name": "chrome",
    "browser_version": "138.0.7178.0",
    "os_name": "linux",
    "os_version": "22.04",
    "revision": "3f4a8517af",
    "full_revision_hash": "3f4a8517af3b047ca875353ca483b634b00d9d15",
    "created_at": "2025-05-14T23:16:13.171816+00:00",
    "time_start": "2025-05-14T19:14:59.285000+00:00",
    "results_url": "https://storage.googleapis.com/wptd/3f4a8517af3b047ca875353ca483b634b00d9d15/chrome-138.0.7178.0-linux-22.04-72d39edad2-summary_v2.json.gz",
    "time_end": "2025-05-14T22:04:38.465000+00:00",
    "raw_results_url": "https://storage.googleapis.com/wptd-results/3f4a8517af3b047ca875353ca483b634b00d9d15/chrome-138.0.7178.0-linux-22.04-72d39edad2/report.json",
    "labels": [
      "canary",
      "chrome",
      "experimental",
      "master",
      "taskcluster",
      "user:jgraham"
    ]
  },
  {
    "id": "5094040439881728",
    "browser_name": "firefox",
    "browser_version": "140.0a1",
    "os_name": "linux",
    "os_version": "22.04",
    "revision": "3f4a8517af",
    "full_revision_hash": "3f4a8517af3b047ca875353ca483b634b00d9d15",
    "created_at": "2025-05-14T23:11:28.400560+00:00",
    "time_start": "2025-05-14T19:24:57.780000+00:00",
    "results_url": "https://storage.googleapis.com/wptd/3f4a8517af3b047ca875353ca483b634b00d9d15/firefox-140.0a1-linux-22.04-61c88a42bc-summary_v2.json.gz",
    "time_end": "2025-05-14T20:37:08.901000+00:00",
    "raw_results_url": "https://storage.googleapis.com/wptd-results/3f4a8517af3b047ca875353ca483b634b00d9d15/firefox-140.0a1-linux-22.04-61c88a42bc/report.json",
    "labels": [
      "experimental",
      "firefox",
      "master",
      "nightly",
      "taskcluster",
      "user:jgraham"
    ]
  }
]