[
  {
    "id": "5087216072392704",
    "browser_name": "chrome",
    "browser_version": "138.0.7188.0",
    "os_name": "linux",
    "os_version": "22.04",
    "revision": "5855958877",
    "full_revision_hash": "5855958877a18ace62a91c0cda77b8848a876635",
    "created_at": "2025-05-19T23:02:31.587838+00:00",
    "time_start": "2025-05-19T19:26:37.123000+00:00",
    "results_url": "https://storage.googleapis.com/wptd/5855958877a18ace62a91c0cda77b8848a876635/chrome-138.0.7188.0-linux-22.04-bddd0bcf2a-summary_v2.json.gz",
    "time_end": "2025-05-19T22:09:24.292000+00:00",
    "raw_results_url": "https://storage.googleapis.com/wptd-results/5855958877a18ace62a91c0cda77b8848a876635/chrome-138.0.7188.0-linux-22.04-bddd0bcf2a/report.json",
    "labels": [
      "canary",
      "chrome",
      "experimental",
      "master",
      "taskcluster",
      "user:chromium-wpt-export-bot"
    ]
  },
  {
    "id": "5116079175368704",
    "browser_name": "firefox",
    "browser_version": "140.0a1",
    "os_name": "linux",
    "os_version": "22.04",
    "revision": "5855958877",
    "full_revision_hash": "5855958877a18ace62a91c0cda77b8848a876635",
    "created_at": "2025-05-19T23:03:11.602609+00:00",
    "time_start": "2025-05-19T19:30:29.181000+00:00",
    "results_url": "https://storage.googleapis.com/wptd/5855958877a18ace62a91c0cda77b8848a876635/firefox-140.0a1-linux-22.04-8f0655b748-summary_v2.json.gz",
    "time_end": "2025-05-19T20:42:35.166000+00:00",
    "raw_results_url": "https://storage.googleapis.com/wptd-results/5855958877a18ace62a91c0cda77b8848a876635/firefox-140.0a1-linux-22.04-8f0655b748/report.json",
    "labels": [
      "experimental",
      "firefox",
      "master",
      "nightly",
      "taskcluster",
      "user:chromium-wpt-export-bot"
    ]
  }
]