[
  {
    "id": 5136057228328960,
    "browser_name": "chrome",
    "browser_version": "134.0.6963.0",
    "os_name": "linux",
    "os_version": "20.04",
    "revision": "baedb5676b",
    "full_revision_hash": "baedb5676be327df5f87c5d18e913ab782baeb65",
    "results_url": "https://storage.googleapis.com/wptd/baedb5676be327df5f87c5d18e913ab782baeb65/chrome-134.0.6963.0-linux-20.04-00a3412da6-summary_v2.json.gz",
    "created_at": "2025-01-18T03:17:17.592910+00:00",
    "time_start": "2025-01-18T00:58:45.696000+00:00",
    "time_end": "2025-01-18T02:29:46.115000+00:00",
    "raw_results_url": "https://storage.googleapis.com/wptd-results/baedb5676be327df5f87c5d18e913ab782baeb65/chrome-134.0.6963.0-linux-20.04-00a3412da6/report.json",
    "labels": [
      "canary",
      "chrome",
      "experimental",
      "master",
      "taskcluster",
      "user:chromium-wpt-export-bot"
    ]
  },
  {
    "id": 5132229942706176,
    "browser_name": "firefox",
    "browser_version": "136.0a1",
    "os_name": "linux",
    "os_version": "20.04",
    "revision": "baedb5676b",
    "full_revision_hash": "baedb5676be327df5f87c5d18e913ab782baeb65",
    "results_url": "https://storage.googleapis.com/wptd/baedb5676be327df5f87c5d18e913ab782baeb65/firefox-136.0a1-linux-20.04-01d1e302a0-summary_v2.json.gz",
    "created_at": "2025-01-18T03:17:32.370675+00:00",
    "time_start": "2025-01-18T01:01:50.800000+00:00",
    "time_end": "2025-01-18T02:13:04.243000+00:00",
    "raw_results_url": "https://storage.googleapis.com/wptd-results/baedb5676be327df5f87c5d18e913ab782baeb65/firefox-136.0a1-linux-20.04-01d1e302a0/report.json",
    "labels": [
      "experimental",
      "firefox",
      "master",
      "nightly",
      "taskcluster",
      "user:chromium-wpt-export-bot"
    ]
  }
]