[
  {
    "id": "5177613284016128",
    "browser_name": "chrome",
    "browser_version": "141.0.7390.0",
    "os_name": "linux",
    "os_version": "22.04",
    "revision": "6447637596",
    "full_revision_hash": "64476375967a8f1eb06a2b681e7c40468b3b105c",
    "created_at": "2025-09-03T01:13:15.275894+00:00",
    "time_start": "2025-09-02T21:40:44.256000+00:00",
    "results_url": "https://storage.googleapis.com/wptd/64476375967a8f1eb06a2b681e7c40468b3b105c/chrome-141.0.7390.0-linux-22.04-ce185e30b1-summary_v2.json.gz",
    "time_end": "2025-09-03T00:18:53.422000+00:00",
    "raw_results_url": "https://storage.googleapis.com/wptd-results/64476375967a8f1eb06a2b681e7c40468b3b105c/chrome-141.0.7390.0-linux-22.04-ce185e30b1/report.json",
    "labels": [
      "canary",
      "chrome",
      "experimental",
      "master",
      "taskcluster",
      "user:moz-wptsync-bot"
    ]
  },
  {
    "id": "6197064238366720",
    "browser_name": "firefox",
    "browser_version": "144.0a1",
    "os_name": "linux",
    "os_version": "22.04",
    "revision": "6447637596",
    "full_revision_hash": "64476375967a8f1eb06a2b681e7c40468b3b105c",
    "created_at": "2025-09-03T00:52:26.594612+00:00",
    "time_start": "2025-09-02T21:47:32.638000+00:00",
    "results_url": "https://storage.googleapis.com/wptd/64476375967a8f1eb06a2b681e7c40468b3b105c/firefox-144.0a1-linux-22.04-f69776a712-summary_v2.json.gz",
    "time_end": "2025-09-02T23:41:01.938000+00:00",
    "raw_results_url": "https://storage.googleapis.com/wptd-results/64476375967a8f1eb06a2b681e7c40468b3b105c/firefox-144.0a1-linux-22.04-f69776a712/report.json",
    "labels": [
      "experimental",
      "firefox",
      "master",
      "nightly",
      "taskcluster",
      "user:moz-wptsync-bot"
    ]
  }
]