[
  {
    "id": 5117206467182592,
    "browser_name": "chrome",
    "browser_version": "123.0.6288.0",
    "os_name": "linux",
    "os_version": "20.04",
    "revision": "50cdae7b23",
    "full_revision_hash": "50cdae7b23a8ab23a1ebeacc71d254105c710b15",
    "results_url": "https://storage.googleapis.com/wptd/50cdae7b23a8ab23a1ebeacc71d254105c710b15/chrome-123.0.6288.0-linux-20.04-a0314f16ef-summary_v2.json.gz",
    "created_at": "2024-02-08T20:35:37.155512+00:00",
    "time_start": "2024-02-08T17:31:44.879000+00:00",
    "time_end": "2024-02-08T19:19:14.030000+00:00",
    "raw_results_url": "https://storage.googleapis.com/wptd-results/50cdae7b23a8ab23a1ebeacc71d254105c710b15/chrome-123.0.6288.0-linux-20.04-a0314f16ef/report.json",
    "labels": [
      "canary",
      "chrome",
      "experimental",
      "master",
      "taskcluster",
      "user:chromium-wpt-export-bot"
    ]
  },
  {
    "id": 5069196114788352,
    "browser_name": "firefox",
    "browser_version": "124.0a1",
    "os_name": "linux",
    "os_version": "20.04",
    "revision": "50cdae7b23",
    "full_revision_hash": "50cdae7b23a8ab23a1ebeacc71d254105c710b15",
    "results_url": "https://storage.googleapis.com/wptd/50cdae7b23a8ab23a1ebeacc71d254105c710b15/firefox-124.0a1-linux-20.04-596c8c5e59-summary_v2.json.gz",
    "created_at": "2024-02-08T20:25:54.356762+00:00",
    "time_start": "2024-02-08T17:32:55.104000+00:00",
    "time_end": "2024-02-08T19:35:11.156000+00:00",
    "raw_results_url": "https://storage.googleapis.com/wptd-results/50cdae7b23a8ab23a1ebeacc71d254105c710b15/firefox-124.0a1-linux-20.04-596c8c5e59/report.json",
    "labels": [
      "experimental",
      "firefox",
      "master",
      "nightly",
      "taskcluster",
      "user:chromium-wpt-export-bot"
    ]
  },
  {
    "id": 5153932933857280,
    "browser_name": "safari",
    "browser_version": "188 preview",
    "os_name": "mac",
    "os_version": "13.6",
    "revision": "50cdae7b23",
    "full_revision_hash": "50cdae7b23a8ab23a1ebeacc71d254105c710b15",
    "results_url": "https://storage.googleapis.com/wptd/50cdae7b23a8ab23a1ebeacc71d254105c710b15/safari-188_preview-mac-13.6-b5d0d373fe-summary_v2.json.gz",
    "created_at": "2024-02-08T21:24:41.466039+00:00",
    "time_start": "2024-02-08T18:29:18.774000+00:00",
    "time_end": "2024-02-08T20:45:53.547000+00:00",
    "raw_results_url": "https://storage.googleapis.com/wptd-results/50cdae7b23a8ab23a1ebeacc71d254105c710b15/safari-188_preview-mac-13.6-b5d0d373fe/report.json",
    "labels": [
      "azure",
      "experimental",
      "master",
      "preview",
      "safari"
    ]
  }
]