[
  {
    "id": 5078296117379072,
    "browser_name": "chrome",
    "browser_version": "133.0.6838.0",
    "os_name": "linux",
    "os_version": "20.04",
    "revision": "9d26d70dfb",
    "full_revision_hash": "9d26d70dfb655c320177751e1a06b5737b2fb3ac",
    "results_url": "https://storage.googleapis.com/wptd/9d26d70dfb655c320177751e1a06b5737b2fb3ac/chrome-133.0.6838.0-linux-20.04-35f4248460-summary_v2.json.gz",
    "created_at": "2024-11-15T20:22:47.491114+00:00",
    "time_start": "2024-11-15T17:35:06.294000+00:00",
    "time_end": "2024-11-15T19:37:35.085000+00:00",
    "raw_results_url": "https://storage.googleapis.com/wptd-results/9d26d70dfb655c320177751e1a06b5737b2fb3ac/chrome-133.0.6838.0-linux-20.04-35f4248460/report.json",
    "labels": [
      "canary",
      "chrome",
      "experimental",
      "master",
      "taskcluster",
      "user:vitorroriz"
    ]
  },
  {
    "id": 4815539480559616,
    "browser_name": "firefox",
    "browser_version": "134.0a1",
    "os_name": "linux",
    "os_version": "20.04",
    "revision": "9d26d70dfb",
    "full_revision_hash": "9d26d70dfb655c320177751e1a06b5737b2fb3ac",
    "results_url": "https://storage.googleapis.com/wptd/9d26d70dfb655c320177751e1a06b5737b2fb3ac/firefox-134.0a1-linux-20.04-7dcdae05c4-summary_v2.json.gz",
    "created_at": "2024-11-15T20:22:04.937728+00:00",
    "time_start": "2024-11-15T17:39:33.209000+00:00",
    "time_end": "2024-11-15T18:45:05.885000+00:00",
    "raw_results_url": "https://storage.googleapis.com/wptd-results/9d26d70dfb655c320177751e1a06b5737b2fb3ac/firefox-134.0a1-linux-20.04-7dcdae05c4/report.json",
    "labels": [
      "experimental",
      "firefox",
      "master",
      "nightly",
      "taskcluster",
      "user:vitorroriz"
    ]
  }
]