[
  {
    "id": "5153725201252352",
    "browser_name": "chrome",
    "browser_version": "139.0.7257.0",
    "os_name": "linux",
    "os_version": "22.04",
    "revision": "a435bf5be6",
    "full_revision_hash": "a435bf5be6d2b70cb5e246d3f3f111d49e4083db",
    "created_at": "2025-06-24T14:34:32.627628+00:00",
    "time_start": "2025-06-24T10:27:50.844000+00:00",
    "results_url": "https://storage.googleapis.com/wptd/a435bf5be6d2b70cb5e246d3f3f111d49e4083db/chrome-139.0.7257.0-linux-22.04-7b0c21cefc-summary_v2.json.gz",
    "time_end": "2025-06-24T13:15:47.673000+00:00",
    "raw_results_url": "https://storage.googleapis.com/wptd-results/a435bf5be6d2b70cb5e246d3f3f111d49e4083db/chrome-139.0.7257.0-linux-22.04-7b0c21cefc/report.json",
    "labels": [
      "canary",
      "chrome",
      "experimental",
      "master",
      "taskcluster",
      "user:moz-wptsync-bot"
    ]
  },
  {
    "id": "6303081870655488",
    "browser_name": "firefox",
    "browser_version": "142.0a1",
    "os_name": "linux",
    "os_version": "22.04",
    "revision": "a435bf5be6",
    "full_revision_hash": "a435bf5be6d2b70cb5e246d3f3f111d49e4083db",
    "created_at": "2025-06-24T14:09:32.563588+00:00",
    "time_start": "2025-06-24T10:35:29.051000+00:00",
    "results_url": "https://storage.googleapis.com/wptd/a435bf5be6d2b70cb5e246d3f3f111d49e4083db/firefox-142.0a1-linux-22.04-ceda4048f3-summary_v2.json.gz",
    "time_end": "2025-06-24T11:43:47.406000+00:00",
    "raw_results_url": "https://storage.googleapis.com/wptd-results/a435bf5be6d2b70cb5e246d3f3f111d49e4083db/firefox-142.0a1-linux-22.04-ceda4048f3/report.json",
    "labels": [
      "experimental",
      "firefox",
      "master",
      "nightly",
      "taskcluster",
      "user:moz-wptsync-bot"
    ]
  }
]