[
  {
    "id": "5121995221237760",
    "browser_name": "chrome",
    "browser_version": "151.0.7922.2",
    "os_name": "linux",
    "os_version": "22.04",
    "revision": "ceada6282a",
    "full_revision_hash": "ceada6282ac9f3f5bccb4394638e7eac7fcfe676",
    "created_at": "2026-06-30T12:49:46.083922+00:00",
    "time_start": "2026-06-30T10:37:14.651000+00:00",
    "results_url": "https://storage.googleapis.com/wptd/ceada6282ac9f3f5bccb4394638e7eac7fcfe676/chrome-151.0.7922.2-linux-22.04-57ef6a58f7-summary_v2.json.gz",
    "time_end": "2026-06-30T12:27:09.519000+00:00",
    "raw_results_url": "https://storage.googleapis.com/wptd-results/ceada6282ac9f3f5bccb4394638e7eac7fcfe676/chrome-151.0.7922.2-linux-22.04-57ef6a58f7/report.json",
    "labels": [
      "canary",
      "chrome",
      "experimental",
      "master",
      "taskcluster",
      "user:chromium-wpt-export-bot"
    ]
  }
]