[
  {
    "id": "5203967438225408",
    "browser_name": "chrome",
    "browser_version": "142.0.7437.0",
    "os_name": "linux",
    "os_version": "22.04",
    "revision": "7f4a3e1ae6",
    "full_revision_hash": "7f4a3e1ae630cfebf71480e46194ed9c0d7190d5",
    "created_at": "2025-09-27T02:33:17.843506+00:00",
    "time_start": "2025-09-26T22:51:09.276000+00:00",
    "results_url": "https://storage.googleapis.com/wptd/7f4a3e1ae630cfebf71480e46194ed9c0d7190d5/chrome-142.0.7437.0-linux-22.04-e1362cce95-summary_v2.json.gz",
    "time_end": "2025-09-27T01:27:23.913000+00:00",
    "raw_results_url": "https://storage.googleapis.com/wptd-results/7f4a3e1ae630cfebf71480e46194ed9c0d7190d5/chrome-142.0.7437.0-linux-22.04-e1362cce95/report.json",
    "labels": [
      "canary",
      "chrome",
      "experimental",
      "master",
      "taskcluster",
      "user:chromium-wpt-export-bot"
    ]
  },
  {
    "id": "5463524659953664",
    "browser_name": "firefox",
    "browser_version": "145.0a1",
    "os_name": "linux",
    "os_version": "22.04",
    "revision": "7f4a3e1ae6",
    "full_revision_hash": "7f4a3e1ae630cfebf71480e46194ed9c0d7190d5",
    "created_at": "2025-09-27T02:22:26.467875+00:00",
    "time_start": "2025-09-26T23:11:45.761000+00:00",
    "results_url": "https://storage.googleapis.com/wptd/7f4a3e1ae630cfebf71480e46194ed9c0d7190d5/firefox-145.0a1-linux-22.04-bea81c31ec-summary_v2.json.gz",
    "time_end": "2025-09-27T00:17:08.328000+00:00",
    "raw_results_url": "https://storage.googleapis.com/wptd-results/7f4a3e1ae630cfebf71480e46194ed9c0d7190d5/firefox-145.0a1-linux-22.04-bea81c31ec/report.json",
    "labels": [
      "experimental",
      "firefox",
      "master",
      "nightly",
      "taskcluster",
      "user:chromium-wpt-export-bot"
    ]
  }
]