[
  {
    "id": 6243454030184448,
    "browser_name": "chrome",
    "browser_version": "135.0.7025.0",
    "os_name": "linux",
    "os_version": "20.04",
    "revision": "0f972c74ba",
    "full_revision_hash": "0f972c74ba55e8aea7cee19266b2a5873d6e1364",
    "results_url": "https://storage.googleapis.com/wptd/0f972c74ba55e8aea7cee19266b2a5873d6e1364/chrome-135.0.7025.0-linux-20.04-c3a78122f8-summary_v2.json.gz",
    "created_at": "2025-02-20T22:50:40.218139+00:00",
    "time_start": "2025-02-20T20:22:30.985000+00:00",
    "time_end": "2025-02-20T21:38:46.733000+00:00",
    "raw_results_url": "https://storage.googleapis.com/wptd-results/0f972c74ba55e8aea7cee19266b2a5873d6e1364/chrome-135.0.7025.0-linux-20.04-c3a78122f8/report.json",
    "labels": [
      "canary",
      "chrome",
      "experimental",
      "master",
      "taskcluster",
      "user:chromium-wpt-export-bot"
    ]
  },
  {
    "id": 5182879569281024,
    "browser_name": "firefox",
    "browser_version": "137.0a1",
    "os_name": "linux",
    "os_version": "20.04",
    "revision": "0f972c74ba",
    "full_revision_hash": "0f972c74ba55e8aea7cee19266b2a5873d6e1364",
    "results_url": "https://storage.googleapis.com/wptd/0f972c74ba55e8aea7cee19266b2a5873d6e1364/firefox-137.0a1-linux-20.04-1626081df8-summary_v2.json.gz",
    "created_at": "2025-02-20T22:49:08.842435+00:00",
    "time_start": "2025-02-20T20:26:03.638000+00:00",
    "time_end": "2025-02-20T21:44:00.492000+00:00",
    "raw_results_url": "https://storage.googleapis.com/wptd-results/0f972c74ba55e8aea7cee19266b2a5873d6e1364/firefox-137.0a1-linux-20.04-1626081df8/report.json",
    "labels": [
      "experimental",
      "firefox",
      "master",
      "nightly",
      "taskcluster",
      "user:chromium-wpt-export-bot"
    ]
  }
]