[
  {
    "id": 5136454294700032,
    "browser_name": "chrome",
    "browser_version": "135.0.7000.0",
    "os_name": "linux",
    "os_version": "20.04",
    "revision": "d2a0195a7c",
    "full_revision_hash": "d2a0195a7c60e4ce1fee83fc394fa2d71c2b7346",
    "results_url": "https://storage.googleapis.com/wptd/d2a0195a7c60e4ce1fee83fc394fa2d71c2b7346/chrome-135.0.7000.0-linux-20.04-e2fddd8b55-summary_v2.json.gz",
    "created_at": "2025-02-06T16:49:16.806543+00:00",
    "time_start": "2025-02-06T14:35:15.087000+00:00",
    "time_end": "2025-02-06T16:00:55.597000+00:00",
    "raw_results_url": "https://storage.googleapis.com/wptd-results/d2a0195a7c60e4ce1fee83fc394fa2d71c2b7346/chrome-135.0.7000.0-linux-20.04-e2fddd8b55/report.json",
    "labels": [
      "canary",
      "chrome",
      "experimental",
      "master",
      "taskcluster",
      "user:chromium-wpt-export-bot"
    ]
  },
  {
    "id": 5145626298023936,
    "browser_name": "firefox",
    "browser_version": "137.0a1",
    "os_name": "linux",
    "os_version": "20.04",
    "revision": "d2a0195a7c",
    "full_revision_hash": "d2a0195a7c60e4ce1fee83fc394fa2d71c2b7346",
    "results_url": "https://storage.googleapis.com/wptd/d2a0195a7c60e4ce1fee83fc394fa2d71c2b7346/firefox-137.0a1-linux-20.04-a9b96bee5f-summary_v2.json.gz",
    "created_at": "2025-02-06T16:48:19.301829+00:00",
    "time_start": "2025-02-06T14:35:51.677000+00:00",
    "time_end": "2025-02-06T15:47:12.095000+00:00",
    "raw_results_url": "https://storage.googleapis.com/wptd-results/d2a0195a7c60e4ce1fee83fc394fa2d71c2b7346/firefox-137.0a1-linux-20.04-a9b96bee5f/report.json",
    "labels": [
      "experimental",
      "firefox",
      "master",
      "nightly",
      "taskcluster",
      "user:chromium-wpt-export-bot"
    ]
  }
]