[
  {
    "id": 5139122529763328,
    "browser_name": "chrome",
    "browser_version": "121.0.6103.3 dev",
    "os_name": "linux",
    "os_version": "20.04",
    "revision": "2c5fe89e8e",
    "full_revision_hash": "2c5fe89e8eba261ea32e71172f0a6b62db15e45b",
    "results_url": "https://storage.googleapis.com/wptd/2c5fe89e8eba261ea32e71172f0a6b62db15e45b/chrome-121.0.6103.3_dev-linux-20.04-3e20debc20-summary_v2.json.gz",
    "created_at": "2023-11-09T17:10:11.681979+00:00",
    "time_start": "2023-11-09T15:24:27.789000+00:00",
    "time_end": "2023-11-09T16:36:05.039000+00:00",
    "raw_results_url": "https://storage.googleapis.com/wptd-results/2c5fe89e8eba261ea32e71172f0a6b62db15e45b/chrome-121.0.6103.3_dev-linux-20.04-3e20debc20/report.json",
    "labels": [
      "chrome",
      "dev",
      "experimental",
      "master",
      "taskcluster",
      "user:chromium-wpt-export-bot"
    ]
  },
  {
    "id": 5098906779648000,
    "browser_name": "firefox",
    "browser_version": "121.0a1",
    "os_name": "linux",
    "os_version": "20.04",
    "revision": "2c5fe89e8e",
    "full_revision_hash": "2c5fe89e8eba261ea32e71172f0a6b62db15e45b",
    "results_url": "https://storage.googleapis.com/wptd/2c5fe89e8eba261ea32e71172f0a6b62db15e45b/firefox-121.0a1-linux-20.04-87b56805ff-summary_v2.json.gz",
    "created_at": "2023-11-09T17:14:32.033209+00:00",
    "time_start": "2023-11-09T15:27:08.230000+00:00",
    "time_end": "2023-11-09T16:56:20.636000+00:00",
    "raw_results_url": "https://storage.googleapis.com/wptd-results/2c5fe89e8eba261ea32e71172f0a6b62db15e45b/firefox-121.0a1-linux-20.04-87b56805ff/report.json",
    "labels": [
      "experimental",
      "firefox",
      "master",
      "nightly",
      "taskcluster",
      "user:chromium-wpt-export-bot"
    ]
  }
]