[
  {
    "id": "4833560308744192",
    "browser_name": "chrome",
    "browser_version": "149.0.7797.0",
    "os_name": "linux",
    "os_version": "22.04",
    "revision": "3c0a160303",
    "full_revision_hash": "3c0a16030321e889b53538da0ba2cd2bd7d060a9",
    "created_at": "2026-04-17T15:29:01.724327+00:00",
    "time_start": "2026-04-17T12:38:45.310000+00:00",
    "results_url": "https://storage.googleapis.com/wptd/3c0a16030321e889b53538da0ba2cd2bd7d060a9/chrome-149.0.7797.0-linux-22.04-a469f59391-summary_v2.json.gz",
    "time_end": "2026-04-17T14:22:44.216000+00:00",
    "raw_results_url": "https://storage.googleapis.com/wptd-results/3c0a16030321e889b53538da0ba2cd2bd7d060a9/chrome-149.0.7797.0-linux-22.04-a469f59391/report.json",
    "labels": [
      "canary",
      "chrome",
      "experimental",
      "master",
      "taskcluster",
      "user:chromium-wpt-export-bot"
    ]
  },
  {
    "id": "4860550487212032",
    "browser_name": "firefox",
    "browser_version": "151.0a1",
    "os_name": "linux",
    "os_version": "22.04",
    "revision": "3c0a160303",
    "full_revision_hash": "3c0a16030321e889b53538da0ba2cd2bd7d060a9",
    "created_at": "2026-04-17T15:02:42.435668+00:00",
    "time_start": "2026-04-17T13:09:40.963000+00:00",
    "results_url": "https://storage.googleapis.com/wptd/3c0a16030321e889b53538da0ba2cd2bd7d060a9/firefox-151.0a1-linux-22.04-d986c99ee3-summary_v2.json.gz",
    "time_end": "2026-04-17T14:18:35.401000+00:00",
    "raw_results_url": "https://storage.googleapis.com/wptd-results/3c0a16030321e889b53538da0ba2cd2bd7d060a9/firefox-151.0a1-linux-22.04-d986c99ee3/report.json",
    "labels": [
      "experimental",
      "firefox",
      "master",
      "nightly",
      "taskcluster",
      "user:chromium-wpt-export-bot"
    ]
  }
]