[
  {
    "id": 5158113660895232,
    "browser_name": "chrome_android",
    "browser_version": "124.0.6326.0",
    "os_name": "android",
    "os_version": "9",
    "revision": "e62531283e",
    "full_revision_hash": "e62531283e6f5c08323bac71f85abcdf5c808a51",
    "results_url": "https://storage.googleapis.com/wptd/e62531283e6f5c08323bac71f85abcdf5c808a51/chrome_android-124.0.6326.0-android-9-af222e8d21-summary_v2.json.gz",
    "created_at": "2024-02-27T16:29:02.196487+00:00",
    "time_start": "2024-02-27T10:42:38.890000+00:00",
    "time_end": "2024-02-27T13:27:59.345000+00:00",
    "raw_results_url": "https://storage.googleapis.com/wptd-results/e62531283e6f5c08323bac71f85abcdf5c808a51/chrome_android-124.0.6326.0-android-9-af222e8d21/report.json",
    "labels": [
      "chrome_android",
      "chromium-ci-results-uploader",
      "dev",
      "experimental",
      "master"
    ]
  }
]